yappd/__init__.py
yappd/pdict.py
yappd-0.1.0.dist-info/METADATA
yappd-0.1.0.dist-info/WHEEL
yappd-0.1.0.dist-info/licenses/LICENSE
yappd-0.1.0.dist-info/RECORD
