Metadata-Version: 2.3
Name: yappd
Version: 0.1.0
Summary: Add your description here
Author-email: Scott Yeager <yeagersm@gmail.com>
License-File: LICENSE
Requires-Python: >=3.8
Requires-Dist: jsonpickle>=3.2.2
